Metadata-Version: 1.0
Name: cr-distributions
Version: 0.1
Summary: Gaussian and Binomial distributions
Home-page: UNKNOWN
Author: Carlos Rojas V
Author-email: carloseduardo866@hotmail.com
License: UNKNOWN
Platform: UNKNOWN
